twilio/__init__.py
twilio/request_validator.py
twilio/base/__init__.py
twilio/base/client_base.py
twilio/base/deserialize.py
twilio/base/domain.py
twilio/base/exceptions.py
twilio/base/instance_context.py
twilio/base/instance_resource.py
twilio/base/list_resource.py
twilio/base/obsolete.py
twilio/base/page.py
twilio/base/serialize.py
twilio/base/values.py
twilio/base/version.py
twilio/http/__init__.py
twilio/http/async_http_client.py
twilio/http/http_client.py
twilio/http/request.py
twilio/http/response.py
twilio/http/validation_client.py
twilio/jwt/__init__.py
twilio/jwt/access_token/__init__.py
twilio/jwt/access_token/grants.py
twilio/jwt/client/__init__.py
twilio/jwt/taskrouter/__init__.py
twilio/jwt/taskrouter/capabilities.py
twilio/jwt/validation/__init__.py
twilio/rest/__init__.py
twilio/rest/accounts/AccountsBase.py
twilio/rest/accounts/__init__.py
twilio/rest/accounts/v1/__init__.py
twilio/rest/accounts/v1/auth_token_promotion.py
twilio/rest/accounts/v1/bulk_consents.py
twilio/rest/accounts/v1/bulk_contacts.py
twilio/rest/accounts/v1/safelist.py
twilio/rest/accounts/v1/secondary_auth_token.py
twilio/rest/accounts/v1/credential/__init__.py
twilio/rest/accounts/v1/credential/aws.py
twilio/rest/accounts/v1/credential/public_key.py
twilio/rest/api/ApiBase.py
twilio/rest/api/__init__.py
twilio/rest/api/v2010/__init__.py
twilio/rest/api/v2010/account/__init__.py
twilio/rest/api/v2010/account/application.py
twilio/rest/api/v2010/account/authorized_connect_app.py
twilio/rest/api/v2010/account/balance.py
twilio/rest/api/v2010/account/connect_app.py
twilio/rest/api/v2010/account/key.py
twilio/rest/api/v2010/account/new_key.py
twilio/rest/api/v2010/account/new_signing_key.py
twilio/rest/api/v2010/account/notification.py
twilio/rest/api/v2010/account/outgoing_caller_id.py
twilio/rest/api/v2010/account/short_code.py
twilio/rest/api/v2010/account/signing_key.py
twilio/rest/api/v2010/account/token.py
twilio/rest/api/v2010/account/transcription.py
twilio-9.3.6.dist-info/AUTHORS.md
twilio-9.3.6.dist-info/LICENSE
twilio-9.3.6.dist-info/METADATA
twilio-9.3.6.dist-info/WHEEL
twilio-9.3.6.dist-info/top_level.txt
twilio-9.3.6.dist-info/RECORD
